lotr_sdk/__init__.py
lotr_sdk/client.py
lotr_sdk/exceptions.py
lotr_sdk/models.py
lotr_sdk/options.py
lotr_sdk/query.py
owx_lotr_sdk-0.1.1.dist-info/LICENSE
owx_lotr_sdk-0.1.1.dist-info/METADATA
owx_lotr_sdk-0.1.1.dist-info/WHEEL
owx_lotr_sdk-0.1.1.dist-info/RECORD
