Metadata-Version: 2.1
Name: owx-lotr-sdk
Version: 0.1.1
Summary: 
Author: Owen Wiggins
Author-email: o@owx.dev
Requires-Python: >=3.11,<4.0
Classifier: Programming Language :: Python :: 3
Classifier: Programming Language :: Python :: 3.11
Requires-Dist: backoff (>=2.2.1,<3.0.0)
Requires-Dist: pytest (>=7.3.1,<8.0.0)
Requires-Dist: ratelimit (>=2.2.1,<3.0.0)
Requires-Dist: requests-mock (>=1.10.0,<2.0.0)
